bruteforce_password/__init__.py
bruteforce_password/bruteforce_password.py
bruteforce_password/common_passwords.txt
bruteforce_password-0.1.5.dist-info/licenses/LICENSE
bruteforce_password-0.1.5.dist-info/METADATA
bruteforce_password-0.1.5.dist-info/WHEEL
bruteforce_password-0.1.5.dist-info/top_level.txt
bruteforce_password-0.1.5.dist-info/RECORD
