Metadata-Version: 2.4
Name: bruteforce-password
Version: 0.1.5
Summary: A tool to brute-force passwords (for educational purposes)
Home-page: https://github.com/Blaze404/BruteforcePassword
Author: Mustafa Qazi
Author-email: mustafaqazi1998@gmail.com
License: MIT
Project-URL: Source, https://github.com/Blaze404/BruteforcePassword
Project-URL: Tracker, https://github.com/Blaze404/BruteforcePassword/issues
Classifier: Programming Language :: Python :: 3
Classifier: License :: OSI Approved :: MIT License
Requires-Python: >=3.7
License-File: LICENSE
Requires-Dist: tqdm
Dynamic: author
Dynamic: author-email
Dynamic: classifier
Dynamic: description
Dynamic: description-content-type
Dynamic: home-page
Dynamic: license
Dynamic: license-file
Dynamic: project-url
Dynamic: requires-dist
Dynamic: requires-python
Dynamic: summary
